tj_probability_package
