Metadata-Version: 1.0
Name: tj-probability-package
Version: 0.1.2
Summary: Gaussian and Binomial distributions
Home-page: UNKNOWN
Author: Akintayo Jabar
Author-email: tayojabar@gmail.com
License: UNKNOWN
Platform: UNKNOWN
